.gitignore
.travis.yml
MANIFEST.in
README.rst
bootstrap.py
setup.cfg
setup.py
travis.cfg
docs/HISTORY.txt
docs/INSTALL.txt
docs/LICENSE.GPL
docs/LICENSE.txt
src/collective/__init__.py
src/collective.geo.kml.egg-info/PKG-INFO
src/collective.geo.kml.egg-info/SOURCES.txt
src/collective.geo.kml.egg-info/dependency_links.txt
src/collective.geo.kml.egg-info/entry_points.txt
src/collective.geo.kml.egg-info/namespace_packages.txt
src/collective.geo.kml.egg-info/not-zip-safe
src/collective.geo.kml.egg-info/requires.txt
src/collective.geo.kml.egg-info/top_level.txt
src/collective/geo/__init__.py
src/collective/geo/kml/README.txt
src/collective/geo/kml/__init__.py
src/collective/geo/kml/config.py
src/collective/geo/kml/configure.zcml
src/collective/geo/kml/interfaces.py
src/collective/geo/kml/profiles.zcml
src/collective/geo/kml/setuphandlers.py
src/collective/geo/kml/testing.py
src/collective/geo/kml/testing.zcml
src/collective/geo/kml/utils.py
src/collective/geo/kml/browser/__init__.py
src/collective/geo/kml/browser/configure.zcml
src/collective/geo/kml/browser/kmlcontentviewlet.pt
src/collective/geo/kml/browser/kmldocument.pt
src/collective/geo/kml/browser/kmldocument.py
src/collective/geo/kml/browser/kmldocument_macros.pt
src/collective/geo/kml/browser/kmldocument_macros.py
src/collective/geo/kml/browser/kmlopenlayersview.pt
src/collective/geo/kml/browser/kmlopenlayersview.py
src/collective/geo/kml/browser/kmlopenlayersview.txt
src/collective/geo/kml/browser/maplayers.py
src/collective/geo/kml/browser/viewlets.py
src/collective/geo/kml/browser/javascripts/kml_openlayers.js
src/collective/geo/kml/browser/layers_templates/kml_layer.pt
src/collective/geo/kml/browser/layers_templates/kmlviewlet-layer.pt
src/collective/geo/kml/locales/collective.geo.kml.pot
src/collective/geo/kml/locales/rebuild.sh
src/collective/geo/kml/locales/de/LC_MESSAGES/collective.geo.kml.po
src/collective/geo/kml/locales/es/LC_MESSAGES/collective.geo.kml.po
src/collective/geo/kml/locales/fr/LC_MESSAGES/collective.geo.kml.po
src/collective/geo/kml/locales/it/LC_MESSAGES/collective.geo.kml.po
src/collective/geo/kml/locales/nl/LC_MESSAGES/collective.geo.kml.po
src/collective/geo/kml/locales/zh_CN/LC_MESSAGES/collective.geo.kml.po
src/collective/geo/kml/locales/zh_TW/LC_MESSAGES/collective.geo.kml.po
src/collective/geo/kml/profiles/default/actions.xml
