Metadata-Version: 1.1
Name: collective.geo.kml
Version: 3.3
Summary: Kml view for collective.geo
Home-page: https://github.com/collective/collective.geo.kml
Author: Giorgio Borelli
Author-email: giorgio@giorgioborelli.it
License: GPL
Keywords: Zope Plone GIS KML Google Maps Bing OpenLayers
Platform: UNKNOWN
Classifier: Framework :: Plone
Classifier: Topic :: Internet
Classifier: Topic :: Scientific/Engineering :: GIS
Classifier: Programming Language :: Python
